sinol_make_ai_tools/__init__.py
sinol_make_ai_tools/clear_in_out.py
sinol_make_ai_tools/cli.py
sinol_make_ai_tools/create_package.py
sinol_make_ai_tools/create_prompt.py
sinol_make_ai_tools/unserialize_dir.py
sinol_make_ai_tools-0.2.1.dist-info/licenses/LICENSE
sinol_make_ai_tools-0.2.1.dist-info/METADATA
sinol_make_ai_tools-0.2.1.dist-info/WHEEL
sinol_make_ai_tools-0.2.1.dist-info/entry_points.txt
sinol_make_ai_tools-0.2.1.dist-info/top_level.txt
sinol_make_ai_tools-0.2.1.dist-info/RECORD
