Metadata-Version: 2.4
Name: sinol-make-ai-tools
Version: 0.2.1
Summary: A wrapper for sinol-make with tools for generating packages with AI.
Author-email: Wojciech Malinowski <wojciech.malinowski.100@gmail.com>
License-Expression: GPL-3.0
Classifier: Programming Language :: Python :: 3
Classifier: Operating System :: OS Independent
Requires-Python: >=3.8
License-File: LICENSE
Dynamic: license-file
